calculo_idade/__init__.py
calculo_idade/calculo_idade/__init__.py
calculo_idade/calculo_idade/calculo.py
calculo_idade-0.0.1.dist-info/METADATA
calculo_idade-0.0.1.dist-info/WHEEL
calculo_idade-0.0.1.dist-info/top_level.txt
calculo_idade-0.0.1.dist-info/RECORD
