Metadata-Version: 2.1
Name: calculo-idade
Version: 0.0.1
Summary: Calculo de idade por entrada de dados
Home-page: https://github.com/evertonfranca23/exercicio_pypi
Author: DeadLock
License: UNKNOWN
Platform: UNKNOWN
Requires-Python: >=3.5
